setup.cfg
setup.py
provneo4j/__init__.py
provneo4j/api.py
provneo4j/bundle.py
provneo4j/bundle_manager.py
provneo4j/document.py
provneo4j/prov_to_graph.py
provneo4j.egg-info/PKG-INFO
provneo4j.egg-info/SOURCES.txt
provneo4j.egg-info/dependency_links.txt
provneo4j.egg-info/requires.txt
provneo4j.egg-info/top_level.txt
provneo4j/connectors/__init__.py
provneo4j/connectors/connector.py
provneo4j/connectors/deserializer.py
provneo4j/connectors/serializer.py
provneo4j/connectors/neo4j_rest/__init__.py
provneo4j/connectors/neo4j_rest/neo4j.py
provneo4j/connectors/neo4j_rest/neo4j_deserializer.py
provneo4j/connectors/neo4j_rest/neo4j_serializer.py
provneo4j/tests/__init__.py
provneo4j/tests/examples.py
provneo4j/tests/test.py