Metadata-Version: 1.1
Name: provneo4j
Version: 0.3
Summary: Neo4j PROV API client
Home-page: https://github.com/DLR-SC/provneo4j
Author: DLR, Sam Millar, Stefan Bieliauskas
Author-email: opensource@dlr.de, sam@millar.io, sb@conts.de
License: MIT
Keywords: provenance prov graph neo4j
Platform: UNKNOWN
Classifier: Development Status :: 3 - Alpha
Classifier: Topic :: Software Development :: Libraries :: Python Modules
Classifier: Topic :: Scientific/Engineering
Classifier: License :: OSI Approved :: MIT License
Classifier: Programming Language :: Python
